pip_magic/__init__.py
pip_magic-0.2.3.dist-info/LICENSE
pip_magic-0.2.3.dist-info/WHEEL
pip_magic-0.2.3.dist-info/METADATA
pip_magic-0.2.3.dist-info/RECORD
