Metadata-Version: 1.2
Name: pip_magic
Version: 0.2.3
Summary: import this in ipython and use pip magically without ! and correct version !
Home-page: https://github.com/Carreau/pip_magic
License: UNKNOWN
Author: Matthias Bussonnier
Author-email: bussonniermatthias@gmail.com
Classifier: License :: OSI Approved :: MIT License
